ivy_sdk/__init__.py
ivy_sdk/evaluations.py
ivy_sdk/prompts.py
ivy_sdk/sdk.py
ivy_sdk/sdkconfiguration.py
ivy_sdk/tests.py
ivy_sdk/models/__init__.py
ivy_sdk/models/complete_streamingop.py
ivy_sdk/models/completeop.py
ivy_sdk/models/completionresponse.py
ivy_sdk/models/create_evaluationop.py
ivy_sdk/models/create_test_datasetop.py
ivy_sdk/models/create_testcaseop.py
ivy_sdk/models/eval.py
ivy_sdk/models/evaluateop.py
ivy_sdk/models/evaluationdataset.py
ivy_sdk/models/get_test_casesop.py
ivy_sdk/models/health_check_unsecuredop.py
ivy_sdk/models/httpvalidationerror.py
ivy_sdk/models/rootop.py
ivy_sdk/models/run_testsop.py
ivy_sdk/models/sdkerror.py
ivy_sdk/models/security.py
ivy_sdk/models/testcase.py
ivy_sdk/models/testcasecreate.py
ivy_sdk/models/testcaseforeval.py
ivy_sdk/models/testdatasetreturn.py
ivy_sdk/models/validationerror.py
ivy_sdk/utils/__init__.py
ivy_sdk/utils/retries.py
ivy_sdk/utils/utils.py
ivycheck_python-0.8.2.dist-info/LICENSE.md
ivycheck_python-0.8.2.dist-info/METADATA
ivycheck_python-0.8.2.dist-info/WHEEL
ivycheck_python-0.8.2.dist-info/top_level.txt
ivycheck_python-0.8.2.dist-info/RECORD
